editorconfig_cli/__init__.py
editorconfig_cli/main.py
editorconfig_cli-0.1.0.dist-info/LICENSE
editorconfig_cli-0.1.0.dist-info/METADATA
editorconfig_cli-0.1.0.dist-info/WHEEL
editorconfig_cli-0.1.0.dist-info/entry_points.txt
editorconfig_cli-0.1.0.dist-info/RECORD
