Metadata-Version: 2.3
Name: editorconfig-cli
Version: 0.1.0
Summary: editorconfig cli
License: MIT
Author: Hamlet
Author-email: hamlets849@gmail.com
Requires-Python: >=3.9
Classifier: License :: OSI Approved :: MIT License
Classifier: Programming Language :: Python :: 3
Classifier: Programming Language :: Python :: 3.9
Classifier: Programming Language :: Python :: 3.10
Classifier: Programming Language :: Python :: 3.11
Classifier: Programming Language :: Python :: 3.12
Classifier: Programming Language :: Python :: 3.13
Requires-Dist: tinylogging (>=5.0.1,<6.0.0)
